fudgeware/__init__.py
fudgeware/cli.py
fudgeware-0.0.1.dist-info/entry_points.txt
fudgeware-0.0.1.dist-info/LICENSE
fudgeware-0.0.1.dist-info/WHEEL
fudgeware-0.0.1.dist-info/METADATA
fudgeware-0.0.1.dist-info/RECORD
