Metadata-Version: 2.1
Name: fudgeware
Version: 0.0.1
Summary: Create and manage diceware passwords with hash-based dice rolls
Home-page: https://github.com/rlindsgaard/fudgeware
License: MIT
Author: Ronni Elken Lindsgaard
Author-email: ronni.lindsgaard@gmail.com
Requires-Python: >=3.9,<4.0
Classifier: Development Status :: 1 - Planning
Classifier: Environment :: Console
Classifier: Intended Audience :: End Users/Desktop
Classifier: License :: OSI Approved :: MIT License
Classifier: Natural Language :: English
Classifier: Programming Language :: Python :: 3
Classifier: Programming Language :: Python :: 3 :: Only
Classifier: Programming Language :: Python :: 3.10
Classifier: Programming Language :: Python :: 3.9
Classifier: Topic :: Security :: Cryptography
Project-URL: Repository, https://github.com/rlindsgaard/fudgeware
